hyta/SMA.py
hyta/Stochastic_Oscillator.py
hyta/__init__.py
hyta/adx.py
hyta/aroon.py
hyta/atr.py
hyta/bollinger.py
hyta/cci.py
hyta/cmf.py
hyta/cmo.py
hyta/dema.py
hyta/dpo.py
hyta/dx.py
hyta/ema.py
hyta/hma.py
hyta/ichimoku_cloud.py
hyta/kama.py
hyta/macd.py
hyta/mfi.py
hyta/momentum.py
hyta/movingaverage.py
hyta/on_balance_volume.py
hyta/ppo.py
hyta/psar.py
hyta/roc.py
hyta/rsi.py
hyta/t3tillson.py
hyta/tma.py
hyta/tsi.py
hyta/uo.py
hyta/williams_r.py
hyta/wma.py
hyta-0.1.4.dist-info/LICENSE
hyta-0.1.4.dist-info/METADATA
hyta-0.1.4.dist-info/WHEEL
hyta-0.1.4.dist-info/top_level.txt
hyta-0.1.4.dist-info/RECORD
