Metadata-Version: 2.1
Name: hyta
Version: 0.1.4
Summary: Indicators for Hypance Project
Home-page: https://github.com/Hypance/HypanceDataAnalysis
Author: Toygar Aksoy
Author-email: toygar.aksoy@gmail.com
License: MIT
License-File: LICENSE
Requires-Dist: pandas
Requires-Dist: numpy
